{"unknown":"en/ka/y/00/en-kay.html","u":"en/ay/u/00/en-ayu.html","ulsandodud":"en/ul/sa/nd/en-ulsandodud.html","uoan2xoak3j0skq":"en/uo/an/2x/en-uoan2xoak3j0skq.html","uxaonn":"en/ux/ao/nn/en-uxaonn.html","unreve11":"en/un/re/ve/en-unreve11.html","ungdoo":"en/un/gd/oo/en-ungdoo.html","uzzzs2":"en/uz/zz/s2/en-uzzzs2.html","ujjm1004":"en/uj/jm/10/en-ujjm1004.html","udie98":"en/ud/ie/98/en-udie98.html","ueue1004":"en/ue/ue/10/en-ueue1004.html","uayoung":"en/ua/yo/un/en-uayoung.html","uayoung12":"en/ua/yo/un/en-uayoung12.html","unauna99":"en/un/au/na/en-unauna99.html","uxaonnuxaonn":"en/ux/ao/nn/en-uxaonnuxaonn.html"}